[
  {
    "Bac de tri": "Pâteux - EcoDDS vides ou non vides",
    "Produits": "Goudron d'étancheité mur/toiture",
    "EcoDDS ?": "",
    "Consigne ou danger particulier": "",
    "Couleur": "#5B688C"
  },
  {
    "Bac de tri": "Pâteux - EcoDDS vides ou non vides",
    "Produits": "Imprégnant protection (bois,...)",
    "EcoDDS ?": "",
    "Consigne ou danger particulier": "",
    "Couleur": "#5B688C"
  },
  {
    "Bac de tri": "Pâteux - EcoDDS vides ou non vides",
    "Produits": "Joint de plomberie sous forme d'enduit (pâte ou poudre)",
    "EcoDDS ?": "",
    "Consigne ou danger particulier": "",
    "Couleur": "#5B688C"
  },
  {
    "Bac de tri": "Pâteux - EcoDDS vides ou non vides",
    "Produits": "Joint de plomberie mastic vitrier",
    "EcoDDS ?": "",
    "Consigne ou danger particulier": "",
    "Couleur": "#5B688C"
  },
  {
    "Bac de tri": "Pâteux - EcoDDS vides ou non vides",
    "Produits": "Joint de plomberie mastic en cartouche",
    "EcoDDS ?": "",
    "Consigne ou danger particulier": "",
    "Couleur": "#5B688C"
  },
  {
    "Bac de tri": "Pâteux - EcoDDS vides ou non vides",
    "Produits": "Joint de plombetrie mastic (hors mastic vitrier et mastic en cartouche)",
    "EcoDDS ?": "",
    "Consigne ou danger particulier": "",
    "Couleur": "#5B688C"
  },
  {
    "Bac de tri": "Pâteux - EcoDDS vides ou non vides",
    "Produits": "Joint non mastic en poudre oupâte, à base ciment",
    "EcoDDS ?": "",
    "Consigne ou danger particulier": "",
    "Couleur": "#5B688C"
  },
  {
    "Bac de tri": "Pâteux - EcoDDS vides ou non vides",
    "Produits": "Joint silicone d'étanchéité haute performance",
    "EcoDDS ?": "",
    "Consigne ou danger particulier": "",
    "Couleur": "#5B688C"
  },
  {
    "Bac de tri": "Pâteux - EcoDDS vides ou non vides",
    "Produits": "Joint sous forme d'enduit (pâte ou poudre)",
    "EcoDDS ?": "",
    "Consigne ou danger particulier": "",
    "Couleur": "#5B688C"
  },
  {
    "Bac de tri": "Pâteux - EcoDDS vides ou non vides",
    "Produits": "Lasures bois, saturateur, teinte à bois",
    "EcoDDS ?": "",
    "Consigne ou danger particulier": "",
    "Couleur": "#5B688C"
  },
  {
    "Bac de tri": "Pâteux - EcoDDS vides ou non vides",
    "Produits": "Mastic bitumineux",
    "EcoDDS ?": "",
    "Consigne ou danger particulier": "",
    "Couleur": "#5B688C"
  },
  {
    "Bac de tri": "Pâteux - EcoDDS vides ou non vides",
    "Produits": "Mastic en boîte ou pot",
    "EcoDDS ?": "",
    "Consigne ou danger particulier": "",
    "Couleur": "#5B688C"
  },
  {
    "Bac de tri": "Pâteux - EcoDDS vides ou non vides",
    "Produits": "Mastic vitrier (sauf picto comburant)",
    "EcoDDS ?": "",
    "Consigne ou danger particulier": "",
    "Couleur": "#5B688C"
  },
  {
    "Bac de tri": "Pâteux - EcoDDS vides ou non vides",
    "Produits": "Mastic, mastic-colle ou mastic pour joint d'étancheité en cartouche",
    "EcoDDS ?": "",
    "Consigne ou danger particulier": "",
    "Couleur": "#5B688C"
  },
  {
    "Bac de tri": "Pâteux - EcoDDS vides ou non vides",
    "Produits": "Mastic, mastic-colle ou mastic pour joint d'étancheité en pot",
    "EcoDDS ?": "",
    "Consigne ou danger particulier": "",
    "Couleur": "#5B688C"
  },
  {
    "Bac de tri": "Pâteux - EcoDDS vides ou non vides",
    "Produits": "Mortier-colle carrelage",
    "EcoDDS ?": "",
    "Consigne ou danger particulier": "",
    "Couleur": "#5B688C"
  },
  {
    "Bac de tri": "Pâteux - EcoDDS vides ou non vides",
    "Produits": "Mortier divers (pâte ou poudre)",
    "EcoDDS ?": "",
    "Consigne ou danger particulier": "",
    "Couleur": "#5B688C"
  },
  {
    "Bac de tri": "Pâteux - EcoDDS vides ou non vides",
    "Produits": "Paraffine pour le bricolage",
    "EcoDDS ?": "",
    "Consigne ou danger particulier": "",
    "Couleur": "#5B688C"
  },
  {
    "Bac de tri": "Pâteux - EcoDDS vides ou non vides",
    "Produits": "Pâte à bois, rebouchage",
    "EcoDDS ?": "",
    "Consigne ou danger particulier": "",
    "Couleur": "#5B688C"
  },
  {
    "Bac de tri": "Pâteux - EcoDDS vides ou non vides",
    "Produits": "Patine pour meubles",
    "EcoDDS ?": "",
    "Consigne ou danger particulier": "",
    "Couleur": "#5B688C"
  },
  {
    "Bac de tri": "Pâteux - EcoDDS vides ou non vides",
    "Produits": "Peinture en poudre (sauf peinture loisir, peinture industrielle )",
    "EcoDDS ?": "",
    "Consigne ou danger particulier": "",
    "Couleur": "#5B688C"
  },
  {
    "Bac de tri": "Pâteux - EcoDDS vides ou non vides",
    "Produits": "Peintures (croûtes, solides, pâteux) quel qu'en soit le mode d'application (manuel et/ou pistolable)",
    "EcoDDS ?": "",
    "Consigne ou danger particulier": "",
    "Couleur": "#5B688C"
  },
  {
    "Bac de tri": "Pâteux - EcoDDS vides ou non vides",
    "Produits": "Peinturres anti-fouling, antisalissure quel qu'en soit s",
    "EcoDDS ?": "",
    "Consigne ou danger particulier": "",
    "Couleur": "#5B688C"
  },
  {
    "Bac de tri": "Pâteux - EcoDDS vides ou non vides",
    "Produits": "Peintures (croûtes, solides, pâteux) quel qu'en soit le mode d'application (manuel et/ou pistolable)",
    "EcoDDS ?": "",
    "Consigne ou danger particulier": "",
    "Couleur": "#5B688C"
  },
  {
    "Bac de tri": "Pâteux - EcoDDS vides ou non vides",
    "Produits": "Pig",
    "EcoDDS ?": "",
    "Consigne ou danger particulier": "",
    "Couleur": "#5B688C"
  },
  {
    "Bac de tri": "Pâteux - EcoDDS vides ou non vides",
    "Produits": "Primaire d'accrochage, sous-couches",
    "EcoDDS ?": "",
    "Consigne ou danger particulier": "",
    "Couleur": "#5B688C"
  },
  {
    "Bac de tri": "Pâteux - EcoDDS vides ou non vides",
    "Produits": "Ramonage (produits chimiques)",
    "EcoDDS ?": "",
    "Consigne ou danger particulier": "",
    "Couleur": "#5B688C"
  },
  {
    "Bac de tri": "Pâteux - EcoDDS vides ou non vides",
    "Produits": "Résine (non aérosols) : scellement chimique, résine décorative, résine pour le sol, résine pour adhérence etanchéité des mortiers",
    "EcoDDS ?": "",
    "Consigne ou danger particulier": "",
    "Couleur": "#5B688C"
  },
  {
    "Bac de tri": "Pâteux - EcoDDS vides ou non vides",
    "Produits": "Revêtement plastique épais (RPE)",
    "EcoDDS ?": "",
    "Consigne ou danger particulier": "",
    "Couleur": "#5B688C"
  },
  {
    "Bac de tri": "Pâteux - EcoDDS vides ou non vides",
    "Produits": "Sous-couche peinture",
    "EcoDDS ?": "",
    "Consigne ou danger particulier": "",
    "Couleur": "#5B688C"
  }
]